ChangeLog
LICENSE
MANIFEST.in
README.rst
TODO
setup.py
docs/DEPENDENCIES.txt
docs/HISTORY.txt
docs/INSTALL.txt
docs/PRELUDE.txt
docs/USAGE.txt
docs/specs/pre-version-1.0.txt
docs/specs/version-1.0.txt
docs/specs/version-2.0-proposed.txt
docs/specs/version-2.0.txt
examples/ssl/cacert.pem
examples/ssl/client.py
examples/ssl/privkey.pem
examples/ssl/server.py
examples/tcp/client.py
examples/tcp/client_subhandled.py
examples/tcp/server.tac
examples/tcp/server_subhandled.tac
examples/web/client.py
examples/web/server.tac
examples/webAuth/client.py
examples/webAuth/passwd.db
examples/webAuth/server.tac
txJSON_RPC_GaretJax.egg-info/PKG-INFO
txJSON_RPC_GaretJax.egg-info/SOURCES.txt
txJSON_RPC_GaretJax.egg-info/dependency_links.txt
txJSON_RPC_GaretJax.egg-info/top_level.txt
txjsonrpc/__init__.py
txjsonrpc/__init__.pyc
txjsonrpc/auth.py
txjsonrpc/jsonrpc.py
txjsonrpc/jsonrpclib.py
txjsonrpc/meta.py
txjsonrpc/meta.pyc
txjsonrpc/netstring/__init__.py
txjsonrpc/netstring/jsonrpc.py
txjsonrpc/netstring/test/__init__.py
txjsonrpc/netstring/test/test_jsonrpc.py
txjsonrpc/scripts/__init__.py
txjsonrpc/scripts/getVersion.py
txjsonrpc/test/__init__.py
txjsonrpc/test/test_auth.py
txjsonrpc/test/test_jsonrpc.py
txjsonrpc/test/test_jsonrpclib.py
txjsonrpc/testing/__init__.py
txjsonrpc/testing/suite.py
txjsonrpc/util/__init__.py
txjsonrpc/util/__init__.pyc
txjsonrpc/util/dist.py
txjsonrpc/util/dist.pyc
txjsonrpc/web/__init__.py
txjsonrpc/web/jsonrpc.py
txjsonrpc/web/test/__init__.py
txjsonrpc/web/test/test_jsonrpc.py