Metadata-Version: 1.1
Name: txJSON-RPC-GaretJax
Version: 0.3.2
Summary: Code for creatig Twisted JSON-RPC servers and clients.
Home-page: http://launchpad.net/txjsonrpc
Author: Duncan McGreggor
Author-email: oubiwann@adytum.us
License: BSD, GPL
Platform: UNKNOWN
Classifier: Development Status :: 4 - Beta
Classifier: Intended Audience :: Developers
Classifier: Programming Language :: Python
